{
  "grades":["砖注专 ", "砖注专 ", "砖注专 -"],
  "专砖": [
    {
      "砖注专 ": "砖专转",
      "砖注专 ": "砖专转",
      "砖注专 -": "砖专转",
      "砖注": "07:00"
    },
    {
      "砖注专 ": "专转 拽专",
      "砖注专 ": "专转 拽专",
      "砖注专 -": "专转 拽专",
      "砖注": "08:30"
    },
    {
      "砖注专 ": "专 专 - 驻转转 砖注",
      "砖注专 ": "专 砖专",
      "砖注专 -": "",
      "砖注": "09:15"
    },
    {
      "砖注专 ": "住专 拽专",
      "砖注专 ": "住专 拽专",
      "砖注专 -": "住专 拽专",
      "砖注": "10:00"
    },
    {
      "砖注专 ": "砖注专 住",
      "砖注专 ": "砖注专 住",
      "砖注专 -": "砖注专 住",
      "砖注": "12:00"
    },
    {
      "砖注专 ": "专转 爪专",
      "砖注专 ": "专转 爪专",
      "砖注专 -": "专转 爪专",
      "砖注": "13:00"
    },
    {
      "砖注专 ": " 注爪/",
      "砖注专 ": " 注爪/",
      "砖注专 -": " 注爪/",
      "砖注": "13:30"
    },
    {
      "砖注专 ": "",
      "砖注专 ": "",
      "砖注专 -": "",
      "砖注": "15:30"
    },
    {
      "砖注专 ": "砖注专  - 专 专拽 专 注拽",
      "砖注专 ": "砖注专  - 专 专拽 专 注拽",
      "砖注专 -": "砖注专  - 专 专拽 专 注拽",
      "砖注": "15:45"
    },
    {
      "砖注专 ": "注专转",
      "砖注专 ": "注专转",
      "砖注专 -": "注专转",
      "砖注": "17:00"
    },
    {
      "砖注专 ": "  拽转 专转  专转",
      "砖注专 ": "  拽转 专转  专转",
      "砖注专 -": "  拽转 专转  专转",
      "砖注": "17:15"
    },
    {
      "砖注专 ": "专转  转 专砖",
      "砖注专 ": "专转  转 专砖",
      "砖注专 -": "专转  转 专砖",
      "砖注": "18:00"
    },
    {
      "砖注专 ": " 住转  砖转转",
      "砖注专 ": " 住转  砖转转",
      "砖注专 -": " 住转  砖转转",
      "砖注": "19:15"
    },
    {
      "砖注专 ": "住注转 爪 专 转专 砖 砖 专拽",
      "砖注专 ": "住注转 爪 专 转专 砖 砖 专拽",
      "砖注专 -": "住注转 爪 专 转专 砖 砖 专拽",
      "砖注": "20:15"
    }
  ],
  "砖": [
    {"砖注": "07:00", "砖注专 ": "砖专转", "砖注专 ": "砖专转", "砖注专 -":"砖专转"},
    {"砖注": "08:30", "砖注专 ": "专转 拽专", "砖注专 ": "专转 拽专", "砖注专 -":"专转 拽专"},
    {"砖注": "09:15", "砖注专 ": "砖注专  ", "砖注专 ": "砖注专  ", "砖注专 -":"砖注专  "},
    {"砖注": "10:00", "砖注专 ": "住专 拽专", "砖注专 ": "住专 拽专", "砖注专 -":"住专 拽专"},
    {"砖注": "12:00", "砖注专 ": "砖注专 住", "砖注专 ": "砖注专 住", "砖注专 -":"砖注专 住"},
    {"砖注": "13:00", "砖注专 ": "专转 爪专", "砖注专 ": "专转 爪专", "砖注专 -":"专转 爪专"},
    {"砖注": "13:30", "砖注专 ": " 注爪/", "砖注专 ": " 注爪/", "砖注专 -":" 注爪/"},
    {"砖注": "15:30", "砖注专 ": "", "砖注专 ": "", "砖注专 -":""},
    {"砖注": "15:45", "砖注专 ": "砖注专  - 专 ", "砖注专 ": "砖注专  - 专 ", "砖注专 -":"砖注专  - 专 "},
    {
      "砖注专 ": "注专转",
      "砖注专 ": "注专转",
      "砖注专 -": "注专转",
      "砖注": "17:00"
    },
    {
      "砖注专 ": "  拽转 专转  专转",
      "砖注专 ": "  拽转 专转  专转",
      "砖注专 -": "  拽转 专转  专转",
      "砖注": "17:15"
    },
    {
      "砖注专 ": "住转  砖注专转",
      "砖注专 ": "住转  砖注专转",
      "砖注专 -": "住转  砖注专转",
      "砖注": "19:30"
    }
  ],
  "砖砖": [    
    {"砖注": "07:00", "砖注专 ": "砖专转", "砖注专 ": "砖专转", "砖注专 -":"砖专转"},
    {"砖注": "08:30", "砖注专 ": "专转 拽专", "砖注专 ": "专转 拽专", "砖注专 -":"专转 拽专"},
    {"砖注": "09:00", "砖注专 ": " 注拽转 ", "砖注专 ": " 注拽转 ", "砖注专 -":" 注拽转 "}
  ],
  "专注": [
    {"砖注": "07:00", "砖注专 ": "砖专转", "砖注专 ": "砖专转", "砖注专 -":"砖专转"},
    {"砖注": "08:30", "砖注专 ": "专转 拽专", "砖注专 ": "专转 拽专", "砖注专 -":"专转 拽专"},
    {"砖注": "09:15", "砖注专 ": "专 砖专 - 专 专", "砖注专 ": "专 专拽", "砖注专 -":"专 注拽 (','), 专 专 (', ')"},
    {"砖注": "10:00", "砖注专 ": "住专 拽专", "砖注专 ": "住专 拽专", "砖注专 -":"住专 拽专"},
    {"砖注": "12:00", "砖注专 ": "砖注专 住", "砖注专 ": "砖注专 住", "砖注专 -":"砖注专 住"},
    {"砖注": "13:00", "砖注专 ": "专转 爪专", "砖注专 ": "专转 爪专", "砖注专 -":"专转 爪专"},
    {"砖注": "13:30", "砖注专 ": " 注爪/", "砖注专 ": " 注爪/", "砖注专 -":" 注爪/"},
    {"砖注": "15:30", "砖注专 ": "", "砖注专 ": "", "砖注专 -":""},
    {"砖注": "16:00", "砖注专 ": "专   - 住转 转 转\"", "砖注专 ": "专   - 住转 转 转\"", "砖注专 -":"专   - 住转 转 转\""},
    {"砖注": "16:30", "砖注专 ": "住专 爪专", "砖注专 ": "住专 爪专", "砖注专 -":"住专 爪专"},
    {"砖注": "18:00", "砖注专 ": "", "砖注专 ": "住转 砖专", "砖注专 -":"拽\" 驻转  (')"},
    {"砖注": "18:40", "砖注专 ": "专 ", "砖注专 ": "注 驻砖", "砖注专 -":""},
    {"砖注": "19:30", "砖注专 ": "专转 注专", "砖注专 ": "专转 注专", "砖注专 -":"专转 注专"},
    {"砖注": "20:15", "砖注专 ": "注专转", "砖注专 ": "注专转", "砖注专 -":"注专转"},
    {"砖注": "20:30", "砖注专 ": "住专 注专", "砖注专 ": "住专 注专", "砖注专 -":"住专 注专"},
    {"砖注": "22:00", "砖注专 ": "", "砖注专 ": "注专 砖注专", "砖注专 -":""}
  ],
  "砖": [
    {"砖注": "07:00", "砖注专 ": "砖专转", "砖注专 ": "砖专转", "砖注专 -":"砖专转"},
    {"砖注": "08:30", "砖注专 ": "专转 拽专", "砖注专 ": "专转 拽专", "砖注专 -":"专转 拽专"},
    {"砖注": "09:15", "砖注专 ": "住 砖注 (08:45)", "砖注专 ": "专  - 驻\"砖 注 住转", "砖注专 -":"住转 转"},
    {"砖注": "10:00", "砖注专 ": "住专 拽专", "砖注专 ": "住专 拽专", "砖注专 -":"住专 拽专"},
    {"砖注": "12:00", "砖注专 ": "砖注专 ", "砖注专 ": "砖注专 ", "砖注专 -":"砖注专 "},
    {"砖注": "13:00", "砖注专 ": "专转 爪专", "砖注专 ": "专转 爪专", "砖注专 -":"专转 爪专"},
    {"砖注": "13:30", "砖注专 ": " 注爪/", "砖注专 ": " 注爪/", "砖注专 -":" 注爪/"},
    {"砖注": "15:30", "砖注专 ": "", "砖注专 ": "", "砖注专 -":""},
    {"砖注": "15:45", "砖注专 ": "专 砖专 -   注砖", "砖注专 ": "专 砖专 -   注砖", "砖注专 -":"专 砖专 -   注砖"},
    {"砖注": "16:30", "砖注专 ": "专  - 砖注专 ", "砖注专 ": "专  - 砖注专 ", "砖注专 -":"专  - 砖注专 "},
    {"砖注": "18:00", "砖注专 ": "", "砖注专 ": "", "砖注专 -":"专  (', ')"},
    {"砖注": "18:40", "砖注专 ": "专砖 砖 - 驻专砖 砖", "砖注专 ": "专砖 砖 - 驻专砖 砖", "砖注专 -":"专砖 砖 - 驻专砖 砖"},
    {"砖注": "19:30", "砖注专 ": "专转 注专", "砖注专 ": "专转 注专", "砖注专 -":"专转 注专"},
    {"砖注": "20:15", "砖注专 ": "注专转", "砖注专 ": "注专转", "砖注专 -":"注专转"},
    {"砖注": "20:30", "砖注专 ": "住专 注专", "砖注专 ": "住专 注专", "砖注专 -":"住专 注专"}
  ],
  "砖砖": [
    {"砖注": "07:00", "砖注专 ": "砖专转", "砖注专 ": "砖专转", "砖注专 -":"砖专转"},
    {"砖注": "08:30", "砖注专 ": "专转 拽专", "砖注专 ": "专转 拽专", "砖注专 -":"专转 拽专"},
    {"砖注": "09:00", "砖注专 ": " 注爪 转 砖转 拽砖", "砖注专 ": " 注爪 转 砖转 拽砖", "砖注专 -":" 注爪 转 砖转 拽砖"}
  ],
  "砖转": [
  ]
}


